mcp_florence2/__init__.py
mcp_florence2/__main__.py
mcp_florence2/cli.py
mcp_florence2/florence2.py
mcp_florence2/subprocess.py
iflow_mcp_jkawamoto_mcp_florence2-0.3.4.dist-info/METADATA
iflow_mcp_jkawamoto_mcp_florence2-0.3.4.dist-info/WHEEL
iflow_mcp_jkawamoto_mcp_florence2-0.3.4.dist-info/entry_points.txt
iflow_mcp_jkawamoto_mcp_florence2-0.3.4.dist-info/licenses/LICENSE
iflow_mcp_jkawamoto_mcp_florence2-0.3.4.dist-info/RECORD
