Metadata-Version: 2.4
Name: iflow-mcp_jkawamoto_mcp-florence2
Version: 0.3.4
Summary: An MCP server for processing images using Florence-2
Author-email: Junpei Kawamoto <kawamoto.junpei.s64@kyoto-u.jp>
License-File: LICENSE
Classifier: Development Status :: 3 - Alpha
Classifier: License :: OSI Approved :: MIT License
Classifier: Programming Language :: Python :: 3 :: Only
Classifier: Programming Language :: Python :: 3.12
Classifier: Programming Language :: Python :: 3.13
Classifier: Programming Language :: Python :: 3.14
Classifier: Topic :: Scientific/Engineering :: Image Recognition
Requires-Python: >=3.11
Requires-Dist: click<8.3
Requires-Dist: dill>=0.3.9
Requires-Dist: einops>=0.8.1
Requires-Dist: mcp>=1.14
Requires-Dist: pillow>=11.3
Requires-Dist: pydantic>=2.11.9
Requires-Dist: pypdfium2>=4.30
Requires-Dist: requests>=2.32.3
Requires-Dist: rich-click>=1.8.8
Requires-Dist: timm>=1.0.15
Requires-Dist: torch>=2.6
Requires-Dist: transformers>=4.56
